zamp_temporal_sdk-1.0.1.dist-info/METADATA
zamp_temporal_sdk-1.0.1.dist-info/WHEEL
zamp_temporal_sdk-1.0.1.dist-info/licenses/LICENSE
temporalio/service.py
temporalio/bridge/worker.py
temporalio/bridge/Cargo.toml
temporalio/bridge/proto/core_interface_pb2.py
temporalio/bridge/proto/bridge/bridge_pb2.pyi
temporalio/bridge/proto/bridge/__init__.py
temporalio/bridge/proto/bridge/bridge_pb2.py
temporalio/bridge/proto/health/v1/health_pb2.py
temporalio/bridge/proto/health/v1/__init__.py
temporalio/bridge/proto/health/v1/health_pb2.pyi
temporalio/bridge/proto/health/__init__.py
temporalio/bridge/proto/__init__.py
temporalio/bridge/proto/child_workflow/__init__.py
temporalio/bridge/proto/child_workflow/child_workflow_pb2.pyi
temporalio/bridge/proto/child_workflow/child_workflow_pb2.py
temporalio/bridge/proto/core_interface_pb2.pyi
temporalio/bridge/proto/activity_result/activity_result_pb2.py
temporalio/bridge/proto/activity_result/__init__.py
temporalio/bridge/proto/activity_result/activity_result_pb2.pyi
temporalio/bridge/proto/common/common_pb2.pyi
temporalio/bridge/proto/common/common_pb2.py
temporalio/bridge/proto/common/__init__.py
temporalio/bridge/proto/nexus/nexus_pb2.pyi
temporalio/bridge/proto/nexus/__init__.py
temporalio/bridge/proto/nexus/nexus_pb2.py
temporalio/bridge/proto/core_interface_pb2_grpc.pyi
temporalio/bridge/proto/workflow_commands/workflow_commands_pb2.pyi
temporalio/bridge/proto/workflow_commands/__init__.py
temporalio/bridge/proto/workflow_commands/workflow_commands_pb2.py
temporalio/bridge/proto/activity_task/__init__.py
temporalio/bridge/proto/activity_task/activity_task_pb2.pyi
temporalio/bridge/proto/activity_task/activity_task_pb2.py
temporalio/bridge/proto/core_interface_pb2_grpc.py
temporalio/bridge/proto/workflow_activation/__init__.py
temporalio/bridge/proto/workflow_activation/workflow_activation_pb2.py
temporalio/bridge/proto/workflow_activation/workflow_activation_pb2.pyi
temporalio/bridge/proto/external_data/__init__.py
temporalio/bridge/proto/external_data/external_data_pb2.py
temporalio/bridge/proto/external_data/external_data_pb2.pyi
zamp_temporal_sdk-1.0.1.dist-info/RECORD
