Metadata-Version: 2.4
Name: zamp_temporal_sdk
Version: 1.0.1
Requires-Dist: protobuf>=3.20
Requires-Dist: python-dateutil>=2.8.2,<3 ; python_full_version < '3.11'
Requires-Dist: types-protobuf>=3.20
Requires-Dist: typing-extensions>=4.2.0,<5
Requires-Dist: maturin>=1.8.3,<2.0.0
Requires-Dist: grpcio>=1.48.2,<2 ; extra == 'grpc'
Requires-Dist: opentelemetry-api>=1.11.1,<2 ; extra == 'opentelemetry'
Requires-Dist: opentelemetry-sdk>=1.11.1,<2 ; extra == 'opentelemetry'
Requires-Dist: pydantic>=2.0.0,<3 ; extra == 'pydantic'
Provides-Extra: grpc
Provides-Extra: opentelemetry
Provides-Extra: pydantic
License-File: LICENSE
Summary: Temporal.io Python SDK
Keywords: temporal,workflow
Author-email: Temporal Technologies Inc <sdk@temporal.io>
License: MIT
Requires-Python: ~=3.9
Project-URL: Homepage, https://github.com/temporalio/sdk-python
Project-URL: Repository, https://github.com/temporalio/sdk-python
Project-URL: Documentation, https://docs.temporal.io/docs/python
Project-URL: Bug Tracker, https://github.com/temporalio/sdk-python/issues
